{
    "html_attributions": [],
    "next_page_token": "some token",
   
    "results": [
      {
        "business_status": "OPERATIONAL",
        "geometry": {
          "location": {
            "lat": 15.388069,
            "lng": 44.211592
          },
          "viewport": {
            "northeast": {
              "lat": 15.38672,
              "lng": 44.210243
            },
            "southwest": {
              "lat": 15.389418,
              "lng": 44.21294
            }
          }
        },



        "icon": "https://maps.gstatic.com/mapfiles/place_api/icons/v1/png_71/lodging-71.png",
        "name": "السامعي للاطارات والزيوت",
        "opening_hours": {
          "open_now": true
        },
        "photos": [
          {
            "height": 4910,
            "html_attributions": [
              ""
            ],
            "photo_reference": "",
            "width": 6576
          }
        ],
        "place_id": "some place id 61",
        "plus_code": {
          "compound_code": "",
          "global_code": "",
        },
        "rating": 4.2,
        "reference": "",
        "scope": "",
        "types": [
          "بطاريات",
          "زيوت",
          "food",
          "point_of_interest",
          "establishment"
        ],
        "user_ratings_total": 1822,
        "vicinity": "صنعاء شارع تعز"
      },
      {
        "business_status": "OPERATIONAL",
        "geometry": {
            "location": {
                "lat": 15.325529,
                "lng": 44.226389 
              },
              "viewport": {
                "northeast": {
                  "lat": 15.324182,
                  "lng": 44.225077
                },
                "southwest": {
                  "lat": 15.32688,
                  "lng": 44.227775
                }
              }
        },
        "icon": "https://maps.gstatic.com/mapfiles/place_api/icons/v1/png_71/lodging-71.png",
        "name": "مركز امين الجابري لخدمات السيارات",
        "opening_hours": {
          "open_now": true
        },
        "photos": [
          {
            "height": 2048,
            "html_attributions": [
              ""
            ],
            "photo_reference": "",
            "width": 1621
          }
        ],
        "place_id": "some place id 62",
        "plus_code": {
          "compound_code": "",
          "global_code": "",
        },
        "rating": 4.5,
        "reference": "",
        "scope": "",
        "types": [
          "بطاريات",
          "زيوت",
          "فلاتر",
          "point_of_interest",
          "establishment"
        ],
        "user_ratings_total": 8383,
        "vicinity": "صنعاء شارع تعز"
      },
      {
        "business_status": "OPERATIONAL",
        "geometry": {
          "location": {
            "lat": 15.324061,
            "lng": 44.227595
          },
          "viewport": {
            "northeast": {
              "lat": 15.322712,
              "lng": 44.226246
            },
            "southwest": {
              "lat": 15.32541,
              "lng": 44.228944
            }
          }
        },
        "icon": "https://maps.gstatic.com/mapfiles/place_api/icons/v1/png_71/lodging-71.png",
        "name": "شمس الرافدين للتجارة",
        "opening_hours": {
          "open_now": true
        },
        "photos": [
          {
            "height": 1924,
            "html_attributions": [
              ""
            ],
            "photo_reference": "",
            "width": 3598
          }
        ],
        "place_id": "some place id 63",
        "plus_code": {
          "compound_code": "",
          "global_code": "",
        },
        "rating": 4.3,
        "reference": "",
        "scope": "",
        "types": [
          "lodging",
          "bar",
          "restaurant",
          "food",
          "point_of_interest",
          "establishment"
        ],
        "user_ratings_total": 502,
        "vicinity": "ًصنعاء شارع تعز"
      },
      {
        "business_status": "OPERATIONAL",
        "geometry": {
          "location": {
            "lat":  15.323778,
            "lng": 44.227702
          },
          "viewport": {
            "northeast": {
              "lat": 15.322429,
              "lng": 44.226353 
            },
            "southwest": {
              "lat": 15.325127,
              "lng": 44.229051
            }
          }
        },
        "icon": "https://maps.gstatic.com/mapfiles/place_api/icons/v1/png_71/restaurant-71.png",
        "name": "محلات ابن زيد التجارية",
        "photos": [
          {
            "height": 1500,
            "html_attributions": [
              ""
            ],
            "photo_reference": "",
            "width": 2048
          }
        ],
        "place_id": "some place id 64",
        "plus_code": {
          "compound_code": "",
          "global_code": "",
        },
        "rating": 4.4,
        "reference": "",
        "scope": "",
        "types": [
          "restaurant",
          "bar",
          "food",
          "point_of_interest",
          "establishment"
        ],
        "user_ratings_total": 9,
        "vicinity": "صنعاء شارع تعز"
      },
      {
        "business_status": "OPERATIONAL",
        "geometry": {
          "location": {
            "lat": 15.323167,
            "lng": 44.227963
          },
          "viewport": {
            "northeast": {
              "lat": 15.321818,
              "lng": 44.226614
            },
            "southwest": {
              "lat": 15.324516,
              "lng": 44.229312
            }
          }
        },
        "icon": "https://maps.gstatic.com/mapfiles/place_api/icons/v1/png_71/restaurant-71.png",
        "name": "الصياد للتجارة بطاريات والاطارات زيوت",
        "opening_hours": {
          "open_now": false
        },
        "photos": [
          {
            "height": 480,
            "html_attributions": [
              ""
            ],
            "photo_reference": "",
            "width": 640
          }
        ],
        "place_id": "some place id 65",
        "plus_code": {
          "compound_code": "",
          "global_code": "",
        },
        "price_level": 2,
        "rating": 4,
        "reference": "",
        "scope": "",
        "types": [
          "restaurant",
          "night_club",
          "bar",
          "food",
          "point_of_interest",
          "establishment"
        ],
        "user_ratings_total": 1382,
        "vicinity": "33 Yonge Street, Toronto"
      },
      {
        "business_status": "CLOSED_TEMPORARILY",
        "geometry": {
          "location": {
            "lat": 15.323663,
            "lng": 44.229795
          },
          "viewport": {
            "northeast": {
              "lat": 15.322314,
              "lng": 44.228446
            },
            "southwest": {
              "lat": 15.325011,
              "lng": 44.231144
            }
          }
        },
        "icon": "https://maps.gstatic.com/mapfiles/place_api/icons/v1/png_71/restaurant-71.png",
        "name": "بنشر الأمتياز",
        "permanently_closed": true,
        "photos": [
          {
            "height": 3456,
            "html_attributions": [
              ""
            ],
            "photo_reference": "",
            "width": 4608
          }
        ],
        "place_id": "some place id 66",
        "plus_code": {
          "compound_code": "",
          "global_code": "",
        },
        "price_level": 3,
        "rating": 4.5,
        "reference": "",
        "scope": "",
        "types": [
          "restaurant",
          "food",
          "point_of_interest",
          "establishment"
        ],
        "user_ratings_total": 405,
        "vicinity": "صنعاء شارع تعز"
      },
      {
        "business_status": "OPERATIONAL",
        "geometry": {
          "location": {
            "lat": 15.30149,
            "lng": 44.236592
          },
          "viewport": {
            "northeast": {
              "lat": 15.300141,
              "lng": 44.235243
            },
            "southwest": {
              "lat": 15.302839,
              "lng": 44.237941
            }
          }
        },
        "icon": "https://maps.gstatic.com/mapfiles/place_api/icons/v1/png_71/restaurant-71.png",
        "name": "الظفيري للبطاريات",
        "opening_hours": {
          "open_now": true
        },
        "photos": [
          {
            "height": 3840,
            "html_attributions": [
              ""
            ],
            "photo_reference": "",
            "width": 5760
          }
        ],
        "place_id": "some place id 67",
        "plus_code": {
          "compound_code": "",
          "global_code": "",
        },
        "price_level": 2,
        "rating": 4.2,
        "reference": "",
        "scope": "",
        "types": [
          "بطاريات",
          "زيوت",
          "فلاتر",
          "اطارات"
        ],
        "user_ratings_total": 3698,
        "vicinity": "ِشارع تعز"
      },
      {
        "business_status": "CLOSED_TEMPORARILY",
        "geometry": {
          "location": {
            "lat": 15.293813,
            "lng": 44.238438
          },
          "viewport": {
            "northeast": {
              "lat": 15.292464,
              "lng": 44.237089
            },
            "southwest": {
              "lat": 15.295161,
              "lng": 44.239786
            }
          }
        },
        "icon": "https://maps.gstatic.com/mapfiles/place_api/icons/v1/png_71/restaurant-71.png",
        "name": "العليمي للاطارات والبطاريات والزيوت ",
        "permanently_closed": true,
        "photos": [
          {
            "height": 2268,
            "html_attributions": [
              ""
            ],
            "photo_reference": "",
            "width": 4032
          }
        ],
        "place_id": "some place id 68",
        "plus_code": {
          "compound_code": "",
          "global_code": "",
        },
        "price_level": 3,
        "rating": 4.5,
        "reference": "",
        "scope": "",
        "types": [
          "اطارات",
          "بطاريات",
          "زيوت",
          "فلاتر"
        ],
        "user_ratings_total": 2954,
        "vicinity": "صنعاء شارع تعز"
      },
      {
        "business_status": "CLOSED_TEMPORARILY",
        "geometry": {
          "location": {
            "lat": 15.297187,
            "lng": 44.237766 
          },
          "viewport": {
            "northeast": {
              "lat": 15.295838,
              "lng": 44.236417
            },
            "southwest": {
              "lat": 15.298536,
              "lng": 44.239115
            }
          }
        },
        "icon": "https://maps.gstatic.com/mapfiles/place_api/icons/v1/png_71/restaurant-71.png",
        "name": "العليمي لقطع غيار السيارات الاصلية",
        "permanently_closed": true,
        "photos": [
          {
            "height": 636,
            "html_attributions": [
              ""
            ],
            "photo_reference": "",
            "width": 960
          }
        ],
        "place_id": "some place id 69",
        "plus_code": {
          "compound_code": "",
          "global_code": "",
        },
        "price_level": 3,
        "rating": 4.2,
        "reference": "",
        "scope": "",
        "types": [
          "bar",
          "restaurant",
          "food",
          "point_of_interest",
          "establishment"
        ],
        "user_ratings_total": 781,
        "vicinity": "صنعاء شارع تعز"
      },
      {
        "business_status": "OPERATIONAL",
        "geometry": {
          "location": {
            "lat": 15.29626,
            "lng": 44.237299 
          },
          "viewport": {
            "northeast": {
              "lat": 15.294911,
              "lng": 44.23595
            },
            "southwest": {
              "lat": 15.297609,
              "lng": 44.238648
            }
          }
        },
        "icon": "https://maps.gstatic.com/mapfiles/place_api/icons/v1/png_71/restaurant-71.png",
        "name": "ايوب العليمي لتجارة الإطارات",
        "opening_hours": {
          "open_now": false
        },
        "photos": [
          {
            "height": 2048,
            "html_attributions": [
              ""
            ],
            "photo_reference": "",
            "width": 2048
          }
        ],
        "place_id": "some place id 70",
        "plus_code": {
          "compound_code": "",
          "global_code": "",
        },
        "price_level": 2,
        "rating": 4.3,
        "reference": "",
        "scope": "",
        "types": [
          "اطارات",
          "بطاريات"
        
        ],
        "user_ratings_total": 1371,
        "vicinity": "249 Victoria Street, Toronto"
      }
     ],
    "status": "OK"
  }